cad_g4_conv.py
check_overlaps.py
run_vtkviewer.py
cad_g4_conv-1.0.2.dist-info/licenses/LICENSE
cad_g4_conv-1.0.2.dist-info/METADATA
cad_g4_conv-1.0.2.dist-info/WHEEL
cad_g4_conv-1.0.2.dist-info/entry_points.txt
cad_g4_conv-1.0.2.dist-info/top_level.txt
cad_g4_conv-1.0.2.dist-info/RECORD
