Metadata-Version: 2.4
Name: cad-g4-conv
Version: 1.0.2
Summary: CAD to Geant4 GDML converter with automatic mesh repair
Author-email: Fan Lei <drflei@gmail.com>
Maintainer-email: Fan Lei <drflei@gmail.com>
License-Expression: GPL-3.0-or-later
Project-URL: Homepage, https://github.com/drflei/cad_g4_conv
Project-URL: Documentation, https://github.com/drflei/cad_g4_conv/tree/main/docs
Project-URL: Repository, https://github.com/drflei/cad_g4_conv
Project-URL: Issues, https://github.com/drflei/cad_g4_conv/issues
Keywords: geant4,gdml,cad,step,stl,pyg4ometry,geometry,converter,particle-physics,detector,simulation
Classifier: Development Status :: 5 - Production/Stable
Classifier: Intended Audience :: Science/Research
Classifier: Operating System :: OS Independent
Classifier: Programming Language :: Python :: 3
Classifier: Programming Language :: Python :: 3.10
Classifier: Programming Language :: Python :: 3.11
Classifier: Programming Language :: Python :: 3.12
Classifier: Topic :: Scientific/Engineering :: Physics
Classifier: Topic :: Scientific/Engineering :: Visualization
Requires-Python: >=3.10
License-File: LICENSE
Requires-Dist: pyg4ometry>=1.0.0
Requires-Dist: vtk>=9.0.0
Requires-Dist: trimesh
Provides-Extra: dev
Requires-Dist: pytest>=7.0; extra == "dev"
Requires-Dist: black>=22.0; extra == "dev"
Requires-Dist: flake8>=5.0; extra == "dev"
Provides-Extra: overlap
Requires-Dist: geant4_pybind; extra == "overlap"
Provides-Extra: meshlab
Requires-Dist: pymeshlab; extra == "meshlab"
Dynamic: license-file
